{
  "sections": {
    "165302704044b71b07": {
      "type": "custom-liquid",
      "settings": {
        "custom_liquid": "",
        "color_scheme": "accent-1",
        "padding_top": 0,
        "padding_bottom": 0
      }
    },
    "1653036381d417b118": {
      "type": "image-banner",
      "settings": {
        "image": "shopify:\/\/shop_images\/banner11.jpg",
        "image_overlay_opacity": 0,
        "image_height": "large",
        "adapt_height_first_image": false,
        "desktop_content_position": "middle-center",
        "show_text_box": true,
        "desktop_content_alignment": "center",
        "color_scheme": "accent-1",
        "mobile_content_alignment": "center",
        "stack_images_on_mobile": true,
        "show_text_below": true
      }
    },
    "165305418185f8fbc5": {
      "type": "featured-collection",
      "settings": {
        "title": "NEW IN",
        "heading_size": "h1",
        "description": "",
        "show_description": false,
        "description_style": "body",
        "collection": "tee",
        "products_to_show": 8,
        "columns_desktop": 4,
        "full_width": false,
        "show_view_all": true,
        "view_all_style": "solid",
        "enable_desktop_slider": false,
        "color_scheme": "accent-1",
        "image_ratio": "adapt",
        "show_secondary_image": true,
        "show_vendor": false,
        "show_rating": true,
        "enable_quick_add": false,
        "columns_mobile": "2",
        "swipe_on_mobile": false,
        "padding_top": 36,
        "padding_bottom": 36
      }
    },
    "165301640920778662": {
      "type": "collection-list",
      "blocks": {
        "16530164091513bb0d-1": {
          "type": "featured_collection",
          "settings": {
            "collection": "tee"
          }
        },
        "16530164091513bb0d-2": {
          "type": "featured_collection",
          "settings": {
            "collection": "shirts"
          }
        },
        "55bff5bc-0be4-4f0e-92eb-718cf464a895": {
          "type": "featured_collection",
          "settings": {
            "collection": "pants"
          }
        },
        "fa116bea-e3ee-4f73-97a5-7b673ff12b91": {
          "type": "featured_collection",
          "disabled": true,
          "settings": {
            "collection": "set"
          }
        },
        "16530164091513bb0d-0": {
          "type": "featured_collection",
          "settings": {
            "collection": "accessories"
          }
        },
        "4cb05310-dee0-48f3-bebd-28c32175bade": {
          "type": "featured_collection",
          "disabled": true,
          "settings": {
            "collection": ""
          }
        },
        "27f4f867-8f1d-4462-b7cb-92b8f5066309": {
          "type": "featured_collection",
          "disabled": true,
          "settings": {
            "collection": ""
          }
        },
        "4026c2c7-2d21-416e-a40d-758add4e11d6": {
          "type": "featured_collection",
          "disabled": true,
          "settings": {
            "collection": ""
          }
        }
      },
      "block_order": [
        "16530164091513bb0d-1",
        "16530164091513bb0d-2",
        "55bff5bc-0be4-4f0e-92eb-718cf464a895",
        "fa116bea-e3ee-4f73-97a5-7b673ff12b91",
        "16530164091513bb0d-0",
        "4cb05310-dee0-48f3-bebd-28c32175bade",
        "27f4f867-8f1d-4462-b7cb-92b8f5066309",
        "4026c2c7-2d21-416e-a40d-758add4e11d6"
      ],
      "settings": {
        "title": "",
        "heading_size": "h0",
        "image_ratio": "square",
        "columns_desktop": 4,
        "color_scheme": "accent-1",
        "show_view_all": false,
        "columns_mobile": "1",
        "swipe_on_mobile": true,
        "padding_top": 60,
        "padding_bottom": 36
      }
    },
    "featured_collection": {
      "type": "featured-collection",
      "settings": {
        "title": "BEST SELLERS",
        "heading_size": "h1",
        "description": "",
        "show_description": false,
        "description_style": "body",
        "collection": "shirts",
        "products_to_show": 8,
        "columns_desktop": 4,
        "full_width": false,
        "show_view_all": true,
        "view_all_style": "solid",
        "enable_desktop_slider": false,
        "color_scheme": "accent-1",
        "image_ratio": "adapt",
        "show_secondary_image": true,
        "show_vendor": false,
        "show_rating": true,
        "enable_quick_add": false,
        "columns_mobile": "2",
        "swipe_on_mobile": false,
        "padding_top": 28,
        "padding_bottom": 36
      }
    },
    "1653053970a20205a0": {
      "type": "featured-product",
      "disabled": true,
      "blocks": {
        "16530539709e856e6b-0": {
          "type": "text",
          "settings": {
            "text": "{{ section.settings.product.vendor }}",
            "text_style": "uppercase"
          }
        },
        "16530539709e856e6b-1": {
          "type": "title",
          "settings": {
            "heading_size": "h1"
          }
        },
        "16530539709e856e6b-2": {
          "type": "text",
          "settings": {
            "text": "{{ section.settings.product.metafields.descriptors.subtitle.value }}",
            "text_style": "subtitle"
          }
        },
        "16530539709e856e6b-3": {
          "type": "price",
          "settings": {
          }
        },
        "16530539709e856e6b-4": {
          "type": "variant_picker",
          "settings": {
            "picker_type": "button"
          }
        },
        "16530539709e856e6b-5": {
          "type": "quantity_selector",
          "settings": {
          }
        },
        "16530539709e856e6b-6": {
          "type": "buy_buttons",
          "settings": {
            "show_dynamic_checkout": true
          }
        },
        "16530539709e856e6b-7": {
          "type": "share",
          "settings": {
            "share_label": "Share"
          }
        }
      },
      "block_order": [
        "16530539709e856e6b-0",
        "16530539709e856e6b-1",
        "16530539709e856e6b-2",
        "16530539709e856e6b-3",
        "16530539709e856e6b-4",
        "16530539709e856e6b-5",
        "16530539709e856e6b-6",
        "16530539709e856e6b-7"
      ],
      "settings": {
        "product": "",
        "color_scheme": "accent-1",
        "secondary_background": false,
        "hide_variants": false,
        "enable_video_looping": false,
        "padding_top": 36,
        "padding_bottom": 36
      }
    }
  },
  "order": [
    "165302704044b71b07",
    "1653036381d417b118",
    "165305418185f8fbc5",
    "165301640920778662",
    "featured_collection",
    "1653053970a20205a0"
  ]
}
